adafruit_gc_iot_core.py
adafruit_circuitpython_gc_iot_core-4.0.3.dist-info/licenses/LICENSE
adafruit_circuitpython_gc_iot_core-4.0.3.dist-info/METADATA
adafruit_circuitpython_gc_iot_core-4.0.3.dist-info/WHEEL
adafruit_circuitpython_gc_iot_core-4.0.3.dist-info/top_level.txt
adafruit_circuitpython_gc_iot_core-4.0.3.dist-info/RECORD
