Metadata-Version: 2.4
Name: adafruit-circuitpython-gc-iot-core
Version: 4.0.3
Summary: Google Cloud IoT Core Client for CircuitPython
Author-email: Adafruit Industries <circuitpython@adafruit.com>
License: MIT
Project-URL: Homepage, https://github.com/adafruit/Adafruit_CircuitPython_GC_IOT_CORE
Keywords: adafruit,blinka,circuitpython,micropython,gc_iot_core,gcs,,google,cloud,platform,,cloud,,iot,,core
Classifier: Intended Audience :: Developers
Classifier: Topic :: Software Development :: Libraries
Classifier: Topic :: Software Development :: Embedded Systems
Classifier: Topic :: System :: Hardware
Classifier: License :: OSI Approved :: MIT License
Classifier: Programming Language :: Python :: 3
License-File: LICENSE
Requires-Dist: Adafruit-Blinka
Requires-Dist: adafruit-circuitpython-logging>=4.0.1
Requires-Dist: adafruit-circuitpython-jwt
Requires-Dist: adafruit-circuitpython-hashlib>=1.4.5
Requires-Dist: adafruit-circuitpython-minimqtt>=5.3.2
Requires-Dist: adafruit-circuitpython-rsa>=1.2.12
Requires-Dist: adafruit-circuitpython-esp32spi>=5.0.0
Provides-Extra: optional
Dynamic: license-file
